audit_grpc_service/__init__.py
audit_grpc_service/protos/__init__.py
audit_grpc_service/protos/audit_api_pb2.py
audit_grpc_service/protos/audit_api_pb2_grpc.py
data_grpc_service/__init__.py
data_grpc_service/protos/__init__.py
data_grpc_service/protos/detection_chip_data_api_pb2.py
data_grpc_service/protos/detection_chip_data_api_pb2_grpc.py
data_grpc_service/protos/detection_instance_data_api_pb2.py
data_grpc_service/protos/detection_instance_data_api_pb2_grpc.py
data_grpc_service/protos/image_data_api_pb2.py
data_grpc_service/protos/image_data_api_pb2_grpc.py
geospatial_toolkit_grpc_service/__init__.py
geospatial_toolkit_grpc_service/protos/__init__.py
geospatial_toolkit_grpc_service/protos/elevation_model_api_pb2.py
geospatial_toolkit_grpc_service/protos/elevation_model_api_pb2_grpc.py
geospatial_toolkit_grpc_service/protos/function_api_pb2.py
geospatial_toolkit_grpc_service/protos/function_api_pb2_grpc.py
geospatial_toolkit_grpc_service/protos/mgrs_api_pb2.py
geospatial_toolkit_grpc_service/protos/mgrs_api_pb2_grpc.py
global_vo_grpc_service/__init__.py
global_vo_grpc_service/protos/__init__.py
global_vo_grpc_service/protos/admin_consumption_api_pb2.py
global_vo_grpc_service/protos/admin_consumption_api_pb2_grpc.py
global_vo_grpc_service/protos/admin_contract_range_allotment_api_pb2.py
global_vo_grpc_service/protos/admin_contract_range_allotment_api_pb2_grpc.py
global_vo_grpc_service/protos/admin_customer_api_pb2.py
global_vo_grpc_service/protos/admin_customer_api_pb2_grpc.py
global_vo_grpc_service/protos/admin_system_permission_api_pb2.py
global_vo_grpc_service/protos/admin_system_permission_api_pb2_grpc.py
global_vo_grpc_service/protos/admin_team_api_pb2.py
global_vo_grpc_service/protos/admin_team_api_pb2_grpc.py
global_vo_grpc_service/protos/admin_team_role_api_pb2.py
global_vo_grpc_service/protos/admin_team_role_api_pb2_grpc.py
global_vo_grpc_service/protos/admin_team_role_permission_api_pb2.py
fsai_proto_specs-0.0.419.dist-info/METADATA
fsai_proto_specs-0.0.419.dist-info/WHEEL
fsai_proto_specs-0.0.419.dist-info/RECORD
