Metadata-Version: 2.1
Name: fsai-proto-specs
Version: 0.0.419
Summary: Auto-generated library for use with GRPC API.
Home-page: https://github.com/fsai-dev/fsai-proto-specs
License: MIT
Author: Michael Mohamed
Author-email: michael@foundationstack.com
Requires-Python: >=3.8,<4.0
Classifier: License :: OSI Approved :: MIT License
Classifier: Programming Language :: Python :: 3
Classifier: Programming Language :: Python :: 3.8
Classifier: Programming Language :: Python :: 3.9
Classifier: Programming Language :: Python :: 3.10
Classifier: Programming Language :: Python :: 3.11
Classifier: Programming Language :: Python :: 3.12
Requires-Dist: google (>=3.0.0,<4.0.0)
Requires-Dist: grpcio (>=1.47.0,<2.0.0)
Requires-Dist: grpcio-tools (>=1.47.0,<2.0.0)
Requires-Dist: protobuf (>=4.21.11,<5.0.0)
Project-URL: Repository, https://github.com/fsai-dev/fsai-proto-specs
